{
    "manifests": {
        "gonzakpo/websocket-bundle": {
            "manifest": {
                "bundles": {
                    "RollandRock\\WebsocketBundle\\RollandRockWebsocketBundle": [
                        "all"
                    ]
                },
                "copy-from-recipe": {
                    "config/": "%CONFIG_DIR%/"
                },
                "env": {
                    "WEBSOCKET_PORT": "4242"
                }
            },
            "files": {
                "config/packages/gonzakpo_websocket.php": {
                    "contents": [
                        "<?php",
                        "",
                        "declare(strict_types=1);",
                        "",
                        "use Symfony\\Component\\DependencyInjection\\Loader\\Configurator\\ContainerConfigurator;",
                        "",
                        "return static function (ContainerConfigurator $containerConfigurator): void {",
                        "    $containerConfigurator->extension('rolland_rock_websocket', [",
                        "        'port' => '%env(WEBSOCKET_PORT)%',",
                        "    ]);",
                        "};",
                        ""
                    ],
                    "executable": false
                }
            },
            "ref": "067551e289fb78dd6fc777a375bda9eb1f4115a1"
        }
    }
}
