{
    "manifests": {
        "akondas/symfony-consul-bundle": {
            "manifest": {
                "bundles": {
                    "Akondas\\ConsulBundle\\ConsulBundle": [
                        "all"
                    ]
                },
                "copy-from-recipe": {
                    "config/": "%CONFIG_DIR%/"
                },
                "env": {
                    "CONSUL_SERVICE_NAME": "symfony-app",
                    "CONSUL_SERVICE_HOST": "localhost",
                    "CONSUL_SERVICE_PORT": "8000",
                    "CONSUL_CLIENT_BASE_URI": "http://127.0.0.1:8500"
                }
            },
            "files": {
                "config/packages/consul.php": {
                    "contents": [
                        "<?php",
                        "",
                        "declare(strict_types=1);",
                        "",
                        "use Symfony\\Component\\DependencyInjection\\Loader\\Configurator\\ContainerConfigurator;",
                        "",
                        "return static function (ContainerConfigurator $containerConfigurator): void {",
                        "    $containerConfigurator->extension('consul', [",
                        "        'service' => [",
                        "            'name' => '%env(resolve:CONSUL_SERVICE_NAME)%',",
                        "            'host' => '%env(resolve:CONSUL_SERVICE_HOST)%',",
                        "            'port' => '%env(resolve:CONSUL_SERVICE_PORT)%',",
                        "        ],",
                        "        'client' => [",
                        "            'base_uri' => '%env(resolve:CONSUL_CLIENT_BASE_URI)%',",
                        "        ],",
                        "    ]);",
                        "};",
                        ""
                    ],
                    "executable": false
                },
                "config/routes/consul.php": {
                    "contents": [
                        "<?php",
                        "",
                        "declare(strict_types=1);",
                        "",
                        "use Symfony\\Component\\Routing\\Loader\\Configurator\\RoutingConfigurator;",
                        "",
                        "return static function (RoutingConfigurator $routingConfigurator): void {",
                        "    $routingConfigurator->import('@ConsulBundle/Resources/config/routing.yml');",
                        "};",
                        ""
                    ],
                    "executable": false
                }
            },
            "ref": "4f5d0cbaa8699d0ef9161f0970b667944b9a3e04"
        }
    }
}
