{
    "manifests": {
        "kunstmaan/search-bundle": {
            "manifest": {
                "bundles": {
                    "Kunstmaan\\SearchBundle\\KunstmaanSearchBundle": [
                        "all"
                    ]
                },
                "copy-from-recipe": {
                    "config/": "%CONFIG_DIR%/"
                },
                "container": {
                    "kunstmaan_search.elasticsearch_version": "7"
                }
            },
            "files": {
                "config/packages/kunstmaan_search.php": {
                    "contents": [
                        "<?php",
                        "",
                        "declare(strict_types=1);",
                        "",
                        "use Symfony\\Component\\DependencyInjection\\Loader\\Configurator\\ContainerConfigurator;",
                        "",
                        "return static function (ContainerConfigurator $containerConfigurator): void {",
                        "    $containerConfigurator->extension('kunstmaan_search', [",
                        "        'connection' => [",
                        "            'driver' => 'elastic_search',",
                        "            'host' => 'localhost',",
                        "            'port' => 9200,",
                        "        ],",
                        "        'index_prefix' => 'myproject',",
                        "    ]);",
                        "};",
                        ""
                    ],
                    "executable": false
                }
            },
            "ref": "957ea673bfe9d79414ebe498b7ac94131102c1fa"
        }
    }
}
